README.md
setup.py
cbmap/__init__.py
cbmap/cbmap_.py
cbmap.egg-info/PKG-INFO
cbmap.egg-info/SOURCES.txt
cbmap.egg-info/dependency_links.txt
cbmap.egg-info/requires.txt
cbmap.egg-info/top_level.txt